setup.py
ndmtk/LICENSE.txt
ndmtk/README.rst
ndmtk/__init__.py
ndmtk.egg-info/PKG-INFO
ndmtk.egg-info/SOURCES.txt
ndmtk.egg-info/dependency_links.txt
ndmtk.egg-info/requires.txt
ndmtk.egg-info/top_level.txt
ndmtk/plugins/action/__init__.py
ndmtk/plugins/action/ndmtk.j2
ndmtk/plugins/action/ndmtk.py
ndmtk/plugins/action/ndmtk.yml
ndmtk/plugins/action/files/cli/core/openflow.yml
ndmtk/plugins/action/files/cli/os/arista_eos.yml
ndmtk/plugins/action/files/cli/os/cisco_acs.yml
ndmtk/plugins/action/files/cli/os/cisco_asa.yml
ndmtk/plugins/action/files/cli/os/cisco_ios.yml
ndmtk/plugins/action/files/cli/os/cisco_iosxe.yml
ndmtk/plugins/action/files/cli/os/cisco_iosxr.yml
ndmtk/plugins/action/files/cli/os/cisco_ironport.yml
ndmtk/plugins/action/files/cli/os/cisco_nxos.yml
ndmtk/plugins/action/files/cli/os/cisco_nxos_cmp.yml
ndmtk/plugins/action/files/cli/os/cisco_nxos_mds.yml
ndmtk/plugins/action/files/cli/os/cisco_ucs.yml
ndmtk/plugins/action/files/cli/os/citrix_netscaler.yml
ndmtk/plugins/action/files/cli/os/generic_linux.yml
ndmtk/plugins/action/files/cli/os/junos_mx.yml
ndmtk/plugins/action/files/cli/os/junos_qfx.yml
ndmtk/plugins/action/files/cli/os/junos_srx.yml
ndmtk/plugins/action/files/cli/os/nuage_timos.yml
ndmtk/plugins/action/files/cli/os/opengear_linux.yml
ndmtk/plugins/action/files/cli/os/paloalto_panos.yml
ndmtk/plugins/callback/__init__.py
ndmtk/plugins/callback/ndmtk.py
ndmtk/tests/__init__.py
ndmtk/tests/test_utils.py