Metadata-Version: 1.1
Name: ndmtk
Version: 0.2.0
Summary: Network Discovery and Management Toolkit packaged as Ansible Plugin
Home-page: https://github.com/greenpau/ndmtk
Author: Paul Greenberg
Author-email: greenpau@outlook.com
License: OSI Approved :: GNU General Public License v3 or later (GPLv3+)
Download-URL: https://github.com/greenpau/ndmtk/archive/master.zip
Keywords: ansible,ansible plugin,network,ssh,telnet,console,automation,network automation,network discovery
Platform: any
Classifier: Development Status :: 5 - Production/Stable
Classifier: Environment :: Console
Classifier: Intended Audience :: Information Technology
Classifier: Intended Audience :: System Administrators
Classifier: Intended Audience :: Telecommunications Industry
Classifier: License :: OSI Approved :: GNU General Public License v3 or later (GPLv3+)
Classifier: Programming Language :: Python
Classifier: Operating System :: POSIX :: Linux
Classifier: Topic :: Utilities
Classifier: Topic :: System :: Networking
Classifier: Topic :: System :: Networking :: Monitoring
Classifier: Topic :: System :: Systems Administration
